ez_setup.py
scorpio.py
scorpio_gp-0.2.dist-info/LICENSE
scorpio_gp-0.2.dist-info/METADATA
scorpio_gp-0.2.dist-info/WHEEL
scorpio_gp-0.2.dist-info/top_level.txt
scorpio_gp-0.2.dist-info/RECORD
