Metadata-Version: 2.1
Name: scorpio-gp
Version: 0.2
Summary: SCORPIO is a tool for analyze galaxy pairs.
Home-page: https://github.com/josegit88/SCORPIO
Author: ['Jose Benavides']
Author-email: jose.astroph@gmail.com
License: MIT
Keywords: scorpio,survey,images,stacking
Platform: UNKNOWN
Classifier: Development Status :: 4 - Beta
Classifier: Intended Audience :: Education
Classifier: Intended Audience :: Science/Research
Classifier: License :: OSI Approved :: MIT License
Classifier: Operating System :: OS Independent
Classifier: Programming Language :: Python
Classifier: Programming Language :: Python :: 3.7
Classifier: Programming Language :: Python :: Implementation :: CPython
Classifier: Topic :: Scientific/Engineering
Requires-Dist: numpy
Requires-Dist: astropy
Requires-Dist: astroquery
Requires-Dist: matplotlib
Requires-Dist: attrs
Requires-Dist: seaborn
Requires-Dist: retrying
Requires-Dist: scipy
